beaconpy/__init__.py
beaconpy/beacon.py
beaconpy/tests/__init__.py
beaconpy/tests/conftest.py
beaconpy/tests/test_beacon.py
beaconpy-0.1.1.dist-info/licenses/LICENSE
beaconpy-0.1.1.dist-info/METADATA
beaconpy-0.1.1.dist-info/WHEEL
beaconpy-0.1.1.dist-info/top_level.txt
beaconpy-0.1.1.dist-info/RECORD
