Metadata-Version: 2.4
Name: beaconpy
Version: 0.1.1
Summary: A Pythonic implementation of the observer pattern
Home-page: https://github.com/frr149/beaconpy
Author: Fernando Rodriguez Romero
Author-email: Fernando Rodriguez Romero <frr@keepcoding.io>
License-Expression: MIT
Project-URL: Homepage, https://github.com/frr149/beaconpy
Project-URL: Bug Tracker, https://github.com/frr149/beaconpy/issues
Classifier: Programming Language :: Python :: 3
Classifier: Operating System :: OS Independent
Requires-Python: >=3.7
License-File: LICENSE
Dynamic: author
Dynamic: home-page
Dynamic: license-file
Dynamic: requires-python
